git_build_branch/__init__.py
git_build_branch/branch_builder.py
git_build_branch/checkyaml.py
git_build_branch/gitutils.py
git_build_branch/safe_commit_files.py
git_build_branch/sh_verbose.py
git_build_branch-0.1.19.dist-info/licenses/LICENSE
git_build_branch-0.1.19.dist-info/METADATA
git_build_branch-0.1.19.dist-info/WHEEL
git_build_branch-0.1.19.dist-info/entry_points.txt
git_build_branch-0.1.19.dist-info/top_level.txt
git_build_branch-0.1.19.dist-info/RECORD
