Metadata-Version: 2.4
Name: git-build-branch
Version: 0.1.19
Summary: Utility tool for building Git branches my merging multiple other branches together.
Home-page: https://github.com/dimagi/git-build-branch
Author: Dimagi
Author-email: dev@dimagi.com
License: BSD license
Keywords: git-build-branch
Classifier: Development Status :: 2 - Pre-Alpha
Classifier: Intended Audience :: Developers
Classifier: License :: OSI Approved :: BSD License
Classifier: Natural Language :: English
Classifier: Programming Language :: Python :: 2
Classifier: Programming Language :: Python :: 2.7
Classifier: Programming Language :: Python :: 3
Classifier: Programming Language :: Python :: 3.5
Classifier: Programming Language :: Python :: 3.6
Classifier: Programming Language :: Python :: 3.7
Classifier: Programming Language :: Python :: 3.8
License-File: LICENSE
Requires-Dist: Click>=7.0
Requires-Dist: gevent>=1.4.0
Requires-Dist: jsonobject>=0.9.9
Requires-Dist: sh>=2.0.0
Requires-Dist: PyYAML>=5.1
Requires-Dist: contextlib2>=0.5.5
Dynamic: author
Dynamic: author-email
Dynamic: classifier
Dynamic: description
Dynamic: home-page
Dynamic: keywords
Dynamic: license
Dynamic: license-file
Dynamic: requires-dist
Dynamic: summary
